ifpa_api/__init__.py
ifpa_api/client.py
ifpa_api/core/__init__.py
ifpa_api/core/base.py
ifpa_api/core/config.py
ifpa_api/core/exceptions.py
ifpa_api/core/http.py
ifpa_api/core/query_builder.py
ifpa_api/models/__init__.py
ifpa_api/models/calendar.py
ifpa_api/models/common.py
ifpa_api/models/director.py
ifpa_api/models/player.py
ifpa_api/models/rankings.py
ifpa_api/models/reference.py
ifpa_api/models/series.py
ifpa_api/models/stats.py
ifpa_api/models/tournaments.py
ifpa_api/py.typed
ifpa_api/resources/__init__.py
ifpa_api/resources/director/__init__.py
ifpa_api/resources/director/client.py
ifpa_api/resources/director/context.py
ifpa_api/resources/director/query_builder.py
ifpa_api/resources/player/__init__.py
ifpa_api/resources/player/client.py
ifpa_api/resources/player/context.py
ifpa_api/resources/player/query_builder.py
ifpa_api/resources/rankings/__init__.py
ifpa_api/resources/rankings/client.py
ifpa_api/resources/reference/__init__.py
ifpa_api/resources/reference/client.py
ifpa_api/resources/series/__init__.py
ifpa_api/resources/series/client.py
ifpa_api/resources/series/context.py
ifpa_api/resources/series/query_builder.py
ifpa_api/resources/stats/__init__.py
ifpa_api/resources/stats/client.py
ifpa_api/resources/tournament/__init__.py
ifpa_api/resources/tournament/client.py
ifpa_api/resources/tournament/context.py
ifpa_api/resources/tournament/query_builder.py
ifpa_api-0.4.1.dist-info/LICENSE
ifpa_api-0.4.1.dist-info/METADATA
ifpa_api-0.4.1.dist-info/WHEEL
ifpa_api-0.4.1.dist-info/RECORD
