Metadata-Version: 2.1
Name: ifpa-api
Version: 0.4.1
Summary: Typed Python client for the IFPA (International Flipper Pinball Association) API
Home-page: https://github.com/johnsosoka/ifpa-api-python
License: MIT
Keywords: ifpa,pinball,api,client,sdk
Author: John Sosoka
Author-email: im@johnsosoka.com
Requires-Python: >=3.11,<4.0
Classifier: Development Status :: 4 - Beta
Classifier: Intended Audience :: Developers
Classifier: License :: OSI Approved :: MIT License
Classifier: Programming Language :: Python :: 3
Classifier: Programming Language :: Python :: 3.11
Classifier: Programming Language :: Python :: 3.12
Classifier: Topic :: Software Development :: Libraries :: Python Modules
Requires-Dist: pydantic (>=2.0.0,<3.0.0)
Requires-Dist: requests (>=2.31.0,<3.0.0)
Project-URL: Documentation, https://johnsosoka.github.io/ifpa-api-python/
Project-URL: Repository, https://github.com/johnsosoka/ifpa-api-python
